chatcli.py
chatcli-0.1.20.dist-info/WHEEL
chatcli-0.1.20.dist-info/entry_points.txt
chatcli-0.1.20.dist-info/METADATA
chatcli-0.1.20.dist-info/RECORD
