Metadata-Version: 2.1
Name: chatcli
Version: 0.1.20
Summary: Streaming CLI interface for OpenAI's Chat API
License: MIT
Author: IsaacBreen
Author-email: mail@isaacbreen.com
Requires-Python: >=3.10,<4.0
Classifier: License :: OSI Approved :: MIT License
Classifier: Programming Language :: Python :: 3
Classifier: Programming Language :: Python :: 3.10
Classifier: Programming Language :: Python :: 3.11
Requires-Dist: fire (>=0.5.0,<0.6.0)
Requires-Dist: openai (>=0.27.2,<0.28.0)
Requires-Dist: prompt-toolkit (>=3.0.38,<4.0.0)
Requires-Dist: pygments (>=2.14.0,<3.0.0)
Requires-Dist: tiktoken (>=0.3.2,<0.4.0)
